{
    "name":  "Cameron\u0027s App Store",
    "apps":  [
                 {
                     "id":  "video-game-life",
                     "name":  "LevelUp",
                     "tagline":  "Level up your life across nine categories",
                     "description":  "A gamified personal-development tracker. Earn XP and level up across nine life categories, log activities and daily habits, schedule events, and track vices with streaks. Works fully offline.",
                     "version":  "1.5.3",
                     "category":  "Lifestyle",
                     "updated":  "2026-06-02",
                     "icon":  "icons/video-game-life.png",
                     "apk":  "apps/video-game-life-1.5.3.apk",
                     "size":  "26.4 MB",
                     "screenshots":  [

                                     ]
                 }
             ]
}
